{"cameraMode":{"drawMode":0,"name":"Shaded","section":"Shading Mode"},"sceneLighting":false,"audioPlay":false,"sceneViewState":{"m_AlwaysRefresh":false,"showFog":true,"showSkybox":false,"showFlares":true,"showImageEffects":true,"showParticleSystems":true,"showVisualEffectGraphs":true,"m_FxEnabled":true},"in2DMode":false,"pivot":{"x":0.7122244834899902,"y":-2.4993362426757814,"z":1.0506830215454102},"rotation":{"x":-0.21269182860851289,"y":-0.1308761090040207,"z":0.02876104600727558,"w":-0.9678914546966553},"size":6.07082986831665,"orthographic":false}